frame_generator/__init__.py
frame_generator/frame_generator.py
frame_generator/video_info.py
frame_generator-1.0.dist-info/LICENSE
frame_generator-1.0.dist-info/METADATA
frame_generator-1.0.dist-info/WHEEL
frame_generator-1.0.dist-info/top_level.txt
frame_generator-1.0.dist-info/RECORD
