Metadata-Version: 2.1
Name: frame-generator
Version: 1.0
Summary: A module to easily read frames from from a vide and display useful video information.
Home-page: https://github.com/stamas02/frame_generator
Author: Tamas Suveges
Author-email: stamas01@gmail.com
License: MIT
Download-URL: https://github.com/stamas02/frame_generator/archive/v_01.tar.gz
Keywords: vide,frame,frame-reader
Platform: UNKNOWN
Classifier: Development Status :: 4 - Beta
Classifier: Intended Audience :: Developers
Classifier: Topic :: Software Development :: Build Tools
Classifier: License :: OSI Approved :: MIT License
Classifier: Programming Language :: Python :: 3
Classifier: Programming Language :: Python :: 3.4
Classifier: Programming Language :: Python :: 3.5
Classifier: Programming Language :: Python :: 3.6
Classifier: Programming Language :: Python :: 3.7
Classifier: Programming Language :: Python :: 3.8
Requires-Dist: opencv-python
Requires-Dist: tabulate
